aiskill-3.0.2.dist-info/licenses/LICENSE
commands/__init__.py
commands/agents.py
commands/cli.py
commands/discover.py
commands/init.py
commands/lock.py
commands/telemetry_cmd.py
core/__init__.py
core/agent_registry.py
core/config.py
core/design_pattern_detector.py
core/event_store.py
core/graduation_manager.py
core/lock_file.py
core/lsp_analyzer.py
core/mental_analyzer.py
core/migrations.py
core/path_security.py
core/pattern_detector.py
core/sequence_matcher.py
core/session_analyzer.py
core/skill_generator.py
core/skill_tracker.py
core/skillssh_client.py
core/skillssh_publisher.py
core/spec_validator.py
core/telemetry.py
core/unified_suggester.py
core/providers/__init__.py
core/providers/base.py
core/providers/local_provider.py
core/providers/manager.py
core/providers/skillssh_provider.py
core/providers/wellknown_provider.py
hooks/__init__.py
hooks/observer.py
scripts/__init__.py
scripts/discover_skill.py
scripts/get_skill.py
scripts/list_skills.py
scripts/search_skills.py
scripts/skill_registry.py
aiskill-3.0.2.dist-info/METADATA
aiskill-3.0.2.dist-info/WHEEL
aiskill-3.0.2.dist-info/entry_points.txt
aiskill-3.0.2.dist-info/top_level.txt
aiskill-3.0.2.dist-info/RECORD
