Metadata-Version: 2.4
Name: aiskill
Version: 3.0.2
Summary: Automatically learn from your workflows and turn them into intelligent, context-aware skills
Author: MaTriXy
License: MIT
Project-URL: Homepage, https://github.com/MaTriXy/auto-skill
Project-URL: Documentation, https://MaTriXy.github.io/auto-skill/
Project-URL: Repository, https://github.com/MaTriXy/auto-skill
Project-URL: Issues, https://github.com/MaTriXy/auto-skill/issues
Project-URL: Changelog, https://github.com/MaTriXy/auto-skill/blob/main/CHANGELOG.md
Requires-Python: >=3.9
License-File: LICENSE
Requires-Dist: PyYAML>=6.0
Provides-Extra: advanced
Requires-Dist: pygls>=1.3.0; extra == "advanced"
Requires-Dist: tree-sitter>=0.21.0; extra == "advanced"
Requires-Dist: tree-sitter-python; extra == "advanced"
Requires-Dist: numpy>=1.24.0; extra == "advanced"
Requires-Dist: scikit-learn>=1.3.0; extra == "advanced"
Provides-Extra: dev
Requires-Dist: pytest>=7.0; extra == "dev"
Requires-Dist: pytest-cov>=4.0; extra == "dev"
Requires-Dist: black>=23.0; extra == "dev"
Requires-Dist: flake8>=6.0; extra == "dev"
Requires-Dist: mypy>=1.0; extra == "dev"
Provides-Extra: all
Requires-Dist: aiskill[advanced,dev]; extra == "all"
Dynamic: license-file
